rlaif/__init__.py
rlaif-0.0.1.dist-info/METADATA
rlaif-0.0.1.dist-info/WHEEL
rlaif-0.0.1.dist-info/top_level.txt
rlaif-0.0.1.dist-info/RECORD
