Metadata-Version: 2.2
Name: rlaif
Version: 0.0.1
Summary: RLAIF tooling
Author-email: cblagden <chase.blagden@gmail.com>
